README.rst
setup.cfg
setup.py
bin/es-riak
riak_cli_tool/__init__.py
riak_cli_tool.egg-info/PKG-INFO
riak_cli_tool.egg-info/SOURCES.txt
riak_cli_tool.egg-info/dependency_links.txt
riak_cli_tool.egg-info/not-zip-safe
riak_cli_tool.egg-info/requires.txt
riak_cli_tool.egg-info/top_level.txt