Metadata-Version: 1.0
Name: riak-cli-tool
Version: 0.1.6
Summary: Riak tool
Home-page: https://pypi.python.org/pypi/riak_cli_tool
Author: Greg Moselle
Author-email: greg.moselle@enstratius.com
License: Apache 2.0
Platform: UNKNOWN
Classifier: Development Status :: 4 - Beta
Classifier: Natural Language :: English
Classifier: License :: OSI Approved :: Apache Software License
Classifier: Programming Language :: Python
Classifier: Programming Language :: Python :: 2.6
Classifier: Programming Language :: Python :: 2.7
